<?xml version='1.0' encoding='utf-8'?>
<!DOCTYPE hibernate-configuration PUBLIC
    "-//Hibernate/Hibernate Configuration DTD//EN"
    "http://www.hibernate.org/dtd/hibernate-configuration-3.0.dtd">
<hibernate-configuration>
  <session-factory>
    <property name="connection.url">jdbc:sqlserver://QABBDD:1434;database=GLOBALHRPRO140619</property>
    <property name="connection.driver_class">com.microsoft.sqlserver.jdbc.SQLServerDriver</property>
      <mapping class="com.meta4.translationsrobot.ddbb.translators.entities.logicalObject.M4RtrMobjsRdc"/>
      <mapping resource="com/meta4/translationsrobot/ddbb/translators/entities/logicalObject/M4RtrMobjsRdc.hbm.xml"/>
      <!-- <property name="connection.username"/> -->
    <!-- <property name="connection.password"/> -->

    <!-- DB schema will be updated if needed -->
    <!-- <property name="hibernate.hbm2ddl.auto">update</property> -->
  </session-factory>
</hibernate-configuration>